pinhook/__init__.py
pinhook/__version__.py
pinhook/bot.py
pinhook/cli.py
pinhook/log.py
pinhook/plugin.py
pinhook-1.10.1.dist-info/LICENSE
pinhook-1.10.1.dist-info/METADATA
pinhook-1.10.1.dist-info/WHEEL
pinhook-1.10.1.dist-info/entry_points.txt
pinhook-1.10.1.dist-info/top_level.txt
pinhook-1.10.1.dist-info/RECORD
