Metadata-Version: 2.1
Name: pinhook
Version: 1.10.1
Summary: a pluggable irc bot framework in python
Home-page: https://github.com/archangelic/pinhook
Author: M. Hancock
Author-email: mhancock@archangelic.space
License: MIT
Classifier: License :: OSI Approved :: MIT License
Classifier: Development Status :: 5 - Production/Stable
Classifier: Programming Language :: Python
Classifier: Programming Language :: Python :: 3
Classifier: Programming Language :: Python :: 3.4
Classifier: Programming Language :: Python :: 3.5
Classifier: Programming Language :: Python :: 3.6
Classifier: Programming Language :: Python :: 3.7
License-File: LICENSE
Requires-Dist: irc
Requires-Dist: enum34
Requires-Dist: click
Requires-Dist: marshmallow
Provides-Extra: toml
Requires-Dist: toml; extra == "toml"
Provides-Extra: yaml
Requires-Dist: pyyaml; extra == "yaml"
